{
  "name": "alolan-sandshrew",
  "type": "species",
  "img": "/systems/ptr2e/img/icons/species_icon.webp",
  "system": {
    "number": 27,
    "size": {
      "category": "tiny",
      "type": "height"
    },
    "diet": [
      "insectivore"
    ],
    "movement": {
      "primary": [
        {
          "overland": 4
        },
        {
          "burrowing": 4
        }
      ],
      "secondary": []
    },
    "traits": [
      "pokemon",
      "bipedal",
      "underdog",
      "tremorsense",
      "natural-burrower",
      "direction-sense",
      "alolan"
    ],
    "abilities": {
      "starting": [
        "snow-cloak",
        "lets-roll"
      ],
      "basic": [
        "slush-rush",
        "tough-claws"
      ],
      "advanced": [
        "stamina",
        "sharpness"
      ],
      "master": [
        "mountaineer",
        "tuck-and-roll"
      ]
    },
    "skills": {
      "acrobatics": 30,
      "climb": 40,
      "conversation": 20,
      "intimidate": 20,
      "lift": 35,
      "listen": 35,
      "natural-world": 25,
      "navigate": 35,
      "negotiation": 20,
      "running": 35,
      "spot": 15,
      "stealth": 40,
      "swim": 10
    },
    "slug": "",
    "stats": {
      "hp": 0,
      "atk": 0,
      "def": 0,
      "spa": 0,
      "spd": 0,
      "spe": 0
    },
    "types": [
      "untyped"
    ]
  },
  "_id": "uKT634NaMlQjwgUx",
  "effects": [],
  "folder": null,
  "sort": 0,
  "ownership": {
    "default": 0,
    "tXAZ3QUgjuwX4gdV": 3
  },
  "flags": {},
  "_stats": {
    "coreVersion": "12.318",
    "systemId": "ptr2e",
    "systemVersion": "0.001",
    "createdTime": 1712230052166,
    "modifiedTime": 1712230052166,
    "lastModifiedBy": "tXAZ3QUgjuwX4gdV"
  },
  "_key": "!items!uKT634NaMlQjwgUx"
}
