{
  "name": "dustox",
  "type": "species",
  "img": "/systems/ptr2e/img/icons/species_icon.webp",
  "system": {
    "number": 269,
    "size": {
      "category": "small",
      "type": "height"
    },
    "diet": [
      "herbivore"
    ],
    "movement": {
      "primary": [
        {
          "flight": 10
        }
      ],
      "secondary": []
    },
    "traits": [
      "pokemon",
      "winged",
      "darkvision-15",
      "wallclimber",
      "venomous",
      "underdog"
    ],
    "abilities": {
      "starting": [
        "shield-dust",
        "compound-eyes"
      ],
      "basic": [
        "lumberjack",
        "poison-touch"
      ],
      "advanced": [
        "effect-spore",
        "smog-shroud"
      ],
      "master": [
        "majestic-moth",
        "heliophobia"
      ]
    },
    "skills": {
      "climb": 40,
      "conversation": 30,
      "intimidate": 50,
      "lift": 30,
      "listen": 45,
      "natural-world": 55,
      "navigate": 45,
      "negotiation": 30,
      "running": 30,
      "spot": 45,
      "stealth": 40,
      "survival": 50
    },
    "slug": "",
    "stats": {
      "hp": 0,
      "atk": 0,
      "def": 0,
      "spa": 0,
      "spd": 0,
      "spe": 0
    },
    "types": [
      "untyped"
    ]
  },
  "_id": "unsutL4D1ZHXsU6J",
  "effects": [],
  "folder": null,
  "sort": 0,
  "ownership": {
    "default": 0,
    "tXAZ3QUgjuwX4gdV": 3
  },
  "flags": {},
  "_stats": {
    "coreVersion": "12.318",
    "systemId": "ptr2e",
    "systemVersion": "0.001",
    "createdTime": 1712230052166,
    "modifiedTime": 1712230052166,
    "lastModifiedBy": "tXAZ3QUgjuwX4gdV"
  },
  "_key": "!items!unsutL4D1ZHXsU6J"
}
