{
  "name": "meganium",
  "type": "species",
  "img": "/systems/ptr2e/img/icons/species_icon.webp",
  "system": {
    "number": 154,
    "size": {
      "category": "large",
      "type": "quad"
    },
    "diet": [
      "herbivore"
    ],
    "movement": {
      "primary": [
        {
          "overland": 12
        }
      ],
      "secondary": []
    },
    "traits": [
      "pokemon",
      "quadrupedal",
      "plant-grower",
      "reach",
      "calming"
    ],
    "abilities": {
      "starting": [
        "overgrow",
        "leaf-guard"
      ],
      "basic": [
        "blossom-swirl",
        "big-leaves"
      ],
      "advanced": [
        "leaf-shield",
        "sunbathe"
      ],
      "master": [
        "triage",
        "chloroplast"
      ]
    },
    "skills": {
      "acrobatics": 35,
      "conversation": 55,
      "intimidate": 50,
      "lift": 65,
      "listen": 45,
      "natural-world": 55,
      "running": 60,
      "spot": 45,
      "stealth": 50,
      "survival": 60,
      "swim": 40
    },
    "slug": "",
    "stats": {
      "hp": 0,
      "atk": 0,
      "def": 0,
      "spa": 0,
      "spd": 0,
      "spe": 0
    },
    "types": [
      "untyped"
    ]
  },
  "_id": "N4UD73FfRmYSRWLT",
  "effects": [],
  "folder": null,
  "sort": 0,
  "ownership": {
    "default": 0,
    "tXAZ3QUgjuwX4gdV": 3
  },
  "flags": {},
  "_stats": {
    "coreVersion": "12.318",
    "systemId": "ptr2e",
    "systemVersion": "0.001",
    "createdTime": 1712230052166,
    "modifiedTime": 1712230052166,
    "lastModifiedBy": "tXAZ3QUgjuwX4gdV"
  },
  "_key": "!items!N4UD73FfRmYSRWLT"
}
