{
  "name": "omanyte",
  "type": "species",
  "img": "/systems/ptr2e/img/icons/species_icon.webp",
  "system": {
    "number": 138,
    "size": {
      "category": "tiny",
      "type": "height",
      "height": 0.4,
      "weight": 7.5
    },
    "diet": [
      "herbivore"
    ],
    "movement": {
      "primary": [
        {
          "swim": 5
        }
      ],
      "secondary": []
    },
    "traits": [
      "pokemon",
      "fossil",
      "natural-swimmer",
      "gilled",
      "wavesense-15",
      "underdog"
    ],
    "abilities": {
      "starting": [
        "swift-swim",
        "weak-armor"
      ],
      "basic": [
        "fossilized",
        "shell-armor"
      ],
      "advanced": [
        "water-compaction",
        "sturdy"
      ],
      "master": [
        "rain-dish",
        "skill-link"
      ]
    },
    "skills": {
      "acrobatics": 20,
      "climb": 40,
      "intimidate": 25,
      "lift": 35,
      "listen": 30,
      "running": 25,
      "spot": 30,
      "stealth": 25,
      "survival": 35,
      "swim": 45
    },
    "slug": "",
    "stats": {
      "hp": 35,
      "atk": 40,
      "def": 100,
      "spa": 90,
      "spd": 55,
      "spe": 35
    },
    "types": [
      "rock",
      "water"
    ],
    "moves": {
      "egg": [
        {
          "name": "slam",
          "gen": "brilliant-diamond-and-shining-pearl"
        },
        {
          "name": "bite",
          "gen": "brilliant-diamond-and-shining-pearl"
        },
        {
          "name": "supersonic",
          "gen": "brilliant-diamond-and-shining-pearl"
        },
        {
          "name": "bubble-beam",
          "gen": "brilliant-diamond-and-shining-pearl"
        },
        {
          "name": "aurora-beam",
          "gen": "brilliant-diamond-and-shining-pearl"
        },
        {
          "name": "haze",
          "gen": "brilliant-diamond-and-shining-pearl"
        },
        {
          "name": "bide",
          "gen": "ultra-sun-ultra-moon"
        },
        {
          "name": "spikes",
          "gen": "brilliant-diamond-and-shining-pearl"
        },
        {
          "name": "whirlpool",
          "gen": "brilliant-diamond-and-shining-pearl"
        },
        {
          "name": "knock-off",
          "gen": "brilliant-diamond-and-shining-pearl"
        },
        {
          "name": "tickle",
          "gen": "brilliant-diamond-and-shining-pearl"
        },
        {
          "name": "muddy-water",
          "gen": "brilliant-diamond-and-shining-pearl"
        },
        {
          "name": "wring-out",
          "gen": "ultra-sun-ultra-moon"
        },
        {
          "name": "toxic-spikes",
          "gen": "brilliant-diamond-and-shining-pearl"
        },
        {
          "name": "reflect-type",
          "gen": "brilliant-diamond-and-shining-pearl"
        }
      ],
      "tutor": [
        {
          "name": "double-edge",
          "gen": "xd"
        },
        {
          "name": "mimic",
          "gen": "xd"
        },
        {
          "name": "meteor-beam",
          "gen": "sword-shield"
        }
      ],
      "machine": [
        {
          "name": "headbutt",
          "gen": "lets-go-pikachu-lets-go-eevee"
        },
        {
          "name": "body-slam",
          "gen": "sword-shield"
        },
        {
          "name": "take-down",
          "gen": "yellow"
        },
        {
          "name": "surf",
          "gen": "brilliant-diamond-and-shining-pearl"
        },
        {
          "name": "ice-beam",
          "gen": "brilliant-diamond-and-shining-pearl"
        },
        {
          "name": "blizzard",
          "gen": "brilliant-diamond-and-shining-pearl"
        },
        {
          "name": "toxic",
          "gen": "lets-go-pikachu-lets-go-eevee"
        },
        {
          "name": "rage",
          "gen": "yellow"
        },
        {
          "name": "double-team",
          "gen": "brilliant-diamond-and-shining-pearl"
        },
        {
          "name": "reflect",
          "gen": "lets-go-pikachu-lets-go-eevee"
        },
        {
          "name": "waterfall",
          "gen": "brilliant-diamond-and-shining-pearl"
        },
        {
          "name": "rest",
          "gen": "brilliant-diamond-and-shining-pearl"
        },
        {
          "name": "rock-slide",
          "gen": "brilliant-diamond-and-shining-pearl"
        },
        {
          "name": "substitute",
          "gen": "brilliant-diamond-and-shining-pearl"
        },
        {
          "name": "thief",
          "gen": "brilliant-diamond-and-shining-pearl"
        },
        {
          "name": "snore",
          "gen": "sword-shield"
        },
        {
          "name": "curse",
          "gen": "crystal"
        },
        {
          "name": "protect",
          "gen": "brilliant-diamond-and-shining-pearl"
        },
        {
          "name": "icy-wind",
          "gen": "sword-shield"
        },
        {
          "name": "sandstorm",
          "gen": "brilliant-diamond-and-shining-pearl"
        },
        {
          "name": "endure",
          "gen": "brilliant-diamond-and-shining-pearl"
        },
        {
          "name": "swagger",
          "gen": "brilliant-diamond-and-shining-pearl"
        },
        {
          "name": "attract",
          "gen": "brilliant-diamond-and-shining-pearl"
        },
        {
          "name": "sleep-talk",
          "gen": "brilliant-diamond-and-shining-pearl"
        },
        {
          "name": "return",
          "gen": "ultra-sun-ultra-moon"
        },
        {
          "name": "frustration",
          "gen": "ultra-sun-ultra-moon"
        },
        {
          "name": "hidden-power",
          "gen": "ultra-sun-ultra-moon"
        },
        {
          "name": "rain-dance",
          "gen": "brilliant-diamond-and-shining-pearl"
        },
        {
          "name": "rock-smash",
          "gen": "brilliant-diamond-and-shining-pearl"
        },
        {
          "name": "hail",
          "gen": "brilliant-diamond-and-shining-pearl"
        },
        {
          "name": "facade",
          "gen": "brilliant-diamond-and-shining-pearl"
        },
        {
          "name": "secret-power",
          "gen": "omega-ruby-alpha-sapphire"
        },
        {
          "name": "dive",
          "gen": "sword-shield"
        },
        {
          "name": "rock-tomb",
          "gen": "brilliant-diamond-and-shining-pearl"
        },
        {
          "name": "iron-defense",
          "gen": "sword-shield"
        },
        {
          "name": "water-pulse",
          "gen": "brilliant-diamond-and-shining-pearl"
        },
        {
          "name": "gyro-ball",
          "gen": "brilliant-diamond-and-shining-pearl"
        },
        {
          "name": "brine",
          "gen": "brilliant-diamond-and-shining-pearl"
        },
        {
          "name": "natural-gift",
          "gen": "heartgold-soulsilver"
        },
        {
          "name": "rock-polish",
          "gen": "brilliant-diamond-and-shining-pearl"
        },
        {
          "name": "earth-power",
          "gen": "sword-shield"
        },
        {
          "name": "captivate",
          "gen": "heartgold-soulsilver"
        },
        {
          "name": "stealth-rock",
          "gen": "brilliant-diamond-and-shining-pearl"
        },
        {
          "name": "smack-down",
          "gen": "ultra-sun-ultra-moon"
        },
        {
          "name": "round",
          "gen": "sword-shield"
        },
        {
          "name": "scald",
          "gen": "brilliant-diamond-and-shining-pearl"
        },
        {
          "name": "confide",
          "gen": "ultra-sun-ultra-moon"
        }
      ],
      "levelUp": [
        {
          "name": "bind",
          "gen": "brilliant-diamond-and-shining-pearl",
          "level": 1
        },
        {
          "name": "withdraw",
          "gen": "brilliant-diamond-and-shining-pearl",
          "level": 1
        },
        {
          "name": "constrict",
          "gen": "lets-go-pikachu-lets-go-eevee",
          "level": 1
        },
        {
          "name": "rollout",
          "gen": "brilliant-diamond-and-shining-pearl",
          "level": 5
        },
        {
          "name": "sand-attack",
          "gen": "brilliant-diamond-and-shining-pearl",
          "level": 10
        },
        {
          "name": "water-gun",
          "gen": "brilliant-diamond-and-shining-pearl",
          "level": 15
        },
        {
          "name": "leer",
          "gen": "brilliant-diamond-and-shining-pearl",
          "level": 20
        },
        {
          "name": "mud-shot",
          "gen": "brilliant-diamond-and-shining-pearl",
          "level": 25
        },
        {
          "name": "rock-throw",
          "gen": "lets-go-pikachu-lets-go-eevee",
          "level": 26
        },
        {
          "name": "ancient-power",
          "gen": "brilliant-diamond-and-shining-pearl",
          "level": 30
        },
        {
          "name": "horn-attack",
          "gen": "yellow",
          "level": 34
        },
        {
          "name": "rock-blast",
          "gen": "brilliant-diamond-and-shining-pearl",
          "level": 45
        },
        {
          "name": "spike-cannon",
          "gen": "yellow",
          "level": 46
        },
        {
          "name": "shell-smash",
          "gen": "brilliant-diamond-and-shining-pearl",
          "level": 55
        },
        {
          "name": "hydro-pump",
          "gen": "brilliant-diamond-and-shining-pearl",
          "level": 60
        }
      ]
    },
    "captureRate": 45,
    "eggGroups": [
      "water1",
      "water3"
    ],
    "genderRatio": 1,
    "evolutions": {
      "full": {
        "name": "omanyte",
        "details": null,
        "evolutions": [
          {
            "name": "omastar",
            "details": {
              "gender": null,
              "item": null,
              "knownMove": null,
              "level": 40
            },
            "evolutions": []
          }
        ]
      }
    }
  },
  "_id": "PBZ8RyTCBnLz4dha",
  "effects": [],
  "folder": null,
  "sort": 0,
  "ownership": {},
  "flags": {
    "core": {
      "sourceId": "Compendium.ptr2e.core-species.Item.PBZ8RyTCBnLz4dha"
    }
  },
  "_stats": {
    "coreVersion": "12.318",
    "systemId": "ptr2e",
    "systemVersion": "0.001",
    "createdTime": 1712230052166,
    "modifiedTime": 1712321367001,
    "lastModifiedBy": "tXAZ3QUgjuwX4gdV"
  },
  "_key": "!items!PBZ8RyTCBnLz4dha"
}
