{
  "name": "shellos",
  "type": "species",
  "img": "/systems/ptr2e/img/icons/species_icon.webp",
  "system": {
    "number": 422,
    "size": {
      "category": "tiny",
      "type": "quad",
      "height": 0.3,
      "weight": 6.3
    },
    "diet": [
      "omnivore"
    ],
    "movement": {
      "primary": [
        {
          "type": "swim",
          "value": 5
        },
        {
          "type": "overland",
          "value": 5
        }
      ],
      "secondary": []
    },
    "traits": [
      "pokemon",
      "underdog",
      "fountain",
      "natural-swimmer",
      "quadrupedal"
    ],
    "abilities": {
      "starting": [
        "sticky-hold",
        "liquid-ooze"
      ],
      "basic": [
        "storm-drain",
        "dry-skin"
      ],
      "advanced": [
        "sand-force",
        "swift-swim"
      ],
      "master": [
        "dune-terror",
        "no-guard"
      ]
    },
    "skills": {
      "acrobatics": 20,
      "climb": 40,
      "conversation": 30,
      "intimidate": 25,
      "lift": 35,
      "listen": 30,
      "natural-world": 35,
      "navigate": 35,
      "negotiation": 30,
      "running": 15,
      "spot": 30,
      "stealth": 20,
      "survival": 40,
      "swim": 40,
      "track": 20
    },
    "slug": "",
    "stats": {
      "hp": 76,
      "atk": 48,
      "def": 48,
      "spa": 57,
      "spd": 62,
      "spe": 34
    },
    "types": [
      "water"
    ],
    "moves": {
      "levelUp": [
        {
          "name": "water-gun",
          "gen": "scarlet-violet",
          "level": 1
        },
        {
          "name": "mud-slap",
          "gen": "scarlet-violet",
          "level": 1
        },
        {
          "name": "mud-sport",
          "gen": "ultra-sun-ultra-moon",
          "level": 2
        },
        {
          "name": "harden",
          "gen": "scarlet-violet",
          "level": 5
        },
        {
          "name": "recover",
          "gen": "scarlet-violet",
          "level": 10
        },
        {
          "name": "mud-bomb",
          "gen": "ultra-sun-ultra-moon",
          "level": 11
        },
        {
          "name": "water-pulse",
          "gen": "scarlet-violet",
          "level": 15
        },
        {
          "name": "hidden-power",
          "gen": "ultra-sun-ultra-moon",
          "level": 16
        },
        {
          "name": "ancient-power",
          "gen": "scarlet-violet",
          "level": 20
        },
        {
          "name": "body-slam",
          "gen": "scarlet-violet",
          "level": 25
        },
        {
          "name": "muddy-water",
          "gen": "scarlet-violet",
          "level": 31
        },
        {
          "name": "earth-power",
          "gen": "scarlet-violet",
          "level": 35
        },
        {
          "name": "rain-dance",
          "gen": "scarlet-violet",
          "level": 40
        },
        {
          "name": "memento",
          "gen": "scarlet-violet",
          "level": 45
        }
      ],
      "egg": [
        {
          "name": "mist",
          "gen": "scarlet-violet"
        },
        {
          "name": "counter",
          "gen": "scarlet-violet"
        },
        {
          "name": "fissure",
          "gen": "brilliant-diamond-and-shining-pearl"
        },
        {
          "name": "sludge",
          "gen": "scarlet-violet"
        },
        {
          "name": "amnesia",
          "gen": "brilliant-diamond-and-shining-pearl"
        },
        {
          "name": "acid-armor",
          "gen": "scarlet-violet"
        },
        {
          "name": "curse",
          "gen": "scarlet-violet"
        },
        {
          "name": "mirror-coat",
          "gen": "scarlet-violet"
        },
        {
          "name": "stockpile",
          "gen": "scarlet-violet"
        },
        {
          "name": "spit-up",
          "gen": "scarlet-violet"
        },
        {
          "name": "swallow",
          "gen": "scarlet-violet"
        },
        {
          "name": "memento",
          "gen": "brilliant-diamond-and-shining-pearl"
        },
        {
          "name": "yawn",
          "gen": "scarlet-violet"
        },
        {
          "name": "brine",
          "gen": "ultra-sun-ultra-moon"
        },
        {
          "name": "trump-card",
          "gen": "ultra-sun-ultra-moon"
        },
        {
          "name": "clear-smog",
          "gen": "scarlet-violet"
        }
      ],
      "tutor": [
        {
          "name": "headbutt",
          "gen": "heartgold-soulsilver"
        },
        {
          "name": "string-shot",
          "gen": "heartgold-soulsilver"
        },
        {
          "name": "snore",
          "gen": "ultra-sun-ultra-moon"
        },
        {
          "name": "mud-slap",
          "gen": "heartgold-soulsilver"
        },
        {
          "name": "icy-wind",
          "gen": "ultra-sun-ultra-moon"
        },
        {
          "name": "sleep-talk",
          "gen": "black-2-white-2"
        },
        {
          "name": "pain-split",
          "gen": "ultra-sun-ultra-moon"
        },
        {
          "name": "ancient-power",
          "gen": "heartgold-soulsilver"
        },
        {
          "name": "dive",
          "gen": "heartgold-soulsilver"
        },
        {
          "name": "water-pulse",
          "gen": "ultra-sun-ultra-moon"
        },
        {
          "name": "earth-power",
          "gen": "ultra-sun-ultra-moon"
        },
        {
          "name": "skitter-smack",
          "gen": "sword-shield"
        }
      ],
      "machine": [
        {
          "name": "body-slam",
          "gen": "scarlet-violet"
        },
        {
          "name": "take-down",
          "gen": "scarlet-violet"
        },
        {
          "name": "hydro-pump",
          "gen": "scarlet-violet"
        },
        {
          "name": "surf",
          "gen": "scarlet-violet"
        },
        {
          "name": "ice-beam",
          "gen": "scarlet-violet"
        },
        {
          "name": "blizzard",
          "gen": "scarlet-violet"
        },
        {
          "name": "toxic",
          "gen": "ultra-sun-ultra-moon"
        },
        {
          "name": "double-team",
          "gen": "brilliant-diamond-and-shining-pearl"
        },
        {
          "name": "waterfall",
          "gen": "scarlet-violet"
        },
        {
          "name": "amnesia",
          "gen": "scarlet-violet"
        },
        {
          "name": "rest",
          "gen": "scarlet-violet"
        },
        {
          "name": "rock-slide",
          "gen": "scarlet-violet"
        },
        {
          "name": "substitute",
          "gen": "scarlet-violet"
        },
        {
          "name": "snore",
          "gen": "sword-shield"
        },
        {
          "name": "curse",
          "gen": "scarlet-violet"
        },
        {
          "name": "protect",
          "gen": "scarlet-violet"
        },
        {
          "name": "mud-slap",
          "gen": "scarlet-violet"
        },
        {
          "name": "icy-wind",
          "gen": "scarlet-violet"
        },
        {
          "name": "sandstorm",
          "gen": "scarlet-violet"
        },
        {
          "name": "endure",
          "gen": "scarlet-violet"
        },
        {
          "name": "swagger",
          "gen": "brilliant-diamond-and-shining-pearl"
        },
        {
          "name": "attract",
          "gen": "brilliant-diamond-and-shining-pearl"
        },
        {
          "name": "sleep-talk",
          "gen": "scarlet-violet"
        },
        {
          "name": "return",
          "gen": "ultra-sun-ultra-moon"
        },
        {
          "name": "frustration",
          "gen": "ultra-sun-ultra-moon"
        },
        {
          "name": "pain-split",
          "gen": "scarlet-violet"
        },
        {
          "name": "hidden-power",
          "gen": "ultra-sun-ultra-moon"
        },
        {
          "name": "rain-dance",
          "gen": "scarlet-violet"
        },
        {
          "name": "whirlpool",
          "gen": "scarlet-violet"
        },
        {
          "name": "hail",
          "gen": "brilliant-diamond-and-shining-pearl"
        },
        {
          "name": "facade",
          "gen": "scarlet-violet"
        },
        {
          "name": "helping-hand",
          "gen": "scarlet-violet"
        },
        {
          "name": "secret-power",
          "gen": "omega-ruby-alpha-sapphire"
        },
        {
          "name": "dive",
          "gen": "sword-shield"
        },
        {
          "name": "rock-tomb",
          "gen": "scarlet-violet"
        },
        {
          "name": "muddy-water",
          "gen": "scarlet-violet"
        },
        {
          "name": "mud-shot",
          "gen": "scarlet-violet"
        },
        {
          "name": "water-pulse",
          "gen": "scarlet-violet"
        },
        {
          "name": "brine",
          "gen": "brilliant-diamond-and-shining-pearl"
        },
        {
          "name": "natural-gift",
          "gen": "heartgold-soulsilver"
        },
        {
          "name": "earth-power",
          "gen": "scarlet-violet"
        },
        {
          "name": "stone-edge",
          "gen": "scarlet-violet"
        },
        {
          "name": "captivate",
          "gen": "heartgold-soulsilver"
        },
        {
          "name": "stealth-rock",
          "gen": "scarlet-violet"
        },
        {
          "name": "round",
          "gen": "sword-shield"
        },
        {
          "name": "scald",
          "gen": "brilliant-diamond-and-shining-pearl"
        },
        {
          "name": "bulldoze",
          "gen": "scarlet-violet"
        },
        {
          "name": "confide",
          "gen": "ultra-sun-ultra-moon"
        },
        {
          "name": "infestation",
          "gen": "ultra-sun-ultra-moon"
        },
        {
          "name": "liquidation",
          "gen": "scarlet-violet"
        },
        {
          "name": "skitter-smack",
          "gen": "scarlet-violet"
        },
        {
          "name": "tera-blast",
          "gen": "scarlet-violet"
        },
        {
          "name": "snowscape",
          "gen": "scarlet-violet"
        },
        {
          "name": "chilling-water",
          "gen": "scarlet-violet"
        }
      ]
    },
    "captureRate": 190,
    "eggGroups": [
      "water1",
      "indeterminate"
    ],
    "genderRatio": 4,
    "habitats": [],
    "evolutions": {
      "name": "shellos",
      "details": null,
      "evolutions": [
        {
          "name": "gastrodon",
          "uuid": "Compendium.ptr2e.core-species.Item.pwYyAjYBMD9wxy5V",
          "methods": [
            {
              "type": "level",
              "level": 30,
              "operand": "and"
            }
          ],
          "evolutions": [],
          "details": {
            "gender": null,
            "item": null,
            "level": null,
            "knownMove": null
          }
        }
      ],
      "uuid": "Compendium.ptr2e.core-species.Item.Qxxg1K8QcCA5bkBJ"
    }
  },
  "_id": "Qxxg1K8QcCA5bkBJ",
  "effects": [],
  "folder": null,
  "sort": 0,
  "ownership": {
    "default": 0,
    "tXAZ3QUgjuwX4gdV": 3
  },
  "flags": {
    "core": {
      "sourceId": "Compendium.ptr2e.core-species.Item.Qxxg1K8QcCA5bkBJ"
    }
  },
  "_stats": {
    "coreVersion": "12.320",
    "systemId": "ptr2e",
    "systemVersion": "0.004",
    "createdTime": 1712327701027,
    "modifiedTime": 1714663305677,
    "lastModifiedBy": "tXAZ3QUgjuwX4gdV",
    "compendiumSource": "Compendium.ptr2e.core-species.Item.Qxxg1K8QcCA5bkBJ",
    "duplicateSource": null
  },
  "_key": "!items!Qxxg1K8QcCA5bkBJ"
}