{
  "name": "thievul",
  "img": "/systems/ptr2e/img/icons/species_icon.webp",
  "type": "species",
  "system": {
    "types": [
      "dark"
    ],
    "stats": {
      "hp": 70,
      "atk": 58,
      "def": 58,
      "spa": 87,
      "spd": 92,
      "spe": 90
    },
    "moves": {
      "levelUp": [
        {
          "name": "tail-whip",
          "gen": "sword-shield",
          "level": 1
        },
        {
          "name": "quick-attack",
          "gen": "sword-shield",
          "level": 1
        },
        {
          "name": "hone-claws",
          "gen": "sword-shield",
          "level": 1
        },
        {
          "name": "sucker-punch",
          "gen": "sword-shield",
          "level": 28
        },
        {
          "name": "night-slash",
          "gen": "sword-shield",
          "level": 34
        },
        {
          "name": "parting-shot",
          "gen": "sword-shield",
          "level": 52
        }
      ],
      "machine": [
        {
          "name": "hyper-beam",
          "gen": "sword-shield"
        },
        {
          "name": "dig",
          "gen": "sword-shield"
        },
        {
          "name": "psychic",
          "gen": "sword-shield"
        },
        {
          "name": "agility",
          "gen": "sword-shield"
        },
        {
          "name": "screech",
          "gen": "sword-shield"
        },
        {
          "name": "swift",
          "gen": "sword-shield"
        },
        {
          "name": "rest",
          "gen": "sword-shield"
        },
        {
          "name": "substitute",
          "gen": "sword-shield"
        },
        {
          "name": "thief",
          "gen": "sword-shield"
        },
        {
          "name": "snore",
          "gen": "sword-shield"
        },
        {
          "name": "protect",
          "gen": "sword-shield"
        },
        {
          "name": "endure",
          "gen": "sword-shield"
        },
        {
          "name": "attract",
          "gen": "sword-shield"
        },
        {
          "name": "sleep-talk",
          "gen": "sword-shield"
        },
        {
          "name": "baton-pass",
          "gen": "sword-shield"
        },
        {
          "name": "crunch",
          "gen": "sword-shield"
        },
        {
          "name": "shadow-ball",
          "gen": "sword-shield"
        },
        {
          "name": "beat-up",
          "gen": "sword-shield"
        },
        {
          "name": "facade",
          "gen": "sword-shield"
        },
        {
          "name": "taunt",
          "gen": "sword-shield"
        },
        {
          "name": "fake-tears",
          "gen": "sword-shield"
        },
        {
          "name": "mud-shot",
          "gen": "sword-shield"
        },
        {
          "name": "u-turn",
          "gen": "sword-shield"
        },
        {
          "name": "assurance",
          "gen": "sword-shield"
        },
        {
          "name": "dark-pulse",
          "gen": "sword-shield"
        },
        {
          "name": "giga-impact",
          "gen": "sword-shield"
        },
        {
          "name": "nasty-plot",
          "gen": "sword-shield"
        },
        {
          "name": "shadow-claw",
          "gen": "sword-shield"
        },
        {
          "name": "thunder-fang",
          "gen": "sword-shield"
        },
        {
          "name": "ice-fang",
          "gen": "sword-shield"
        },
        {
          "name": "fire-fang",
          "gen": "sword-shield"
        },
        {
          "name": "grass-knot",
          "gen": "sword-shield"
        },
        {
          "name": "foul-play",
          "gen": "sword-shield"
        },
        {
          "name": "round",
          "gen": "sword-shield"
        },
        {
          "name": "acrobatics",
          "gen": "sword-shield"
        },
        {
          "name": "tail-slap",
          "gen": "sword-shield"
        },
        {
          "name": "snarl",
          "gen": "sword-shield"
        },
        {
          "name": "play-rough",
          "gen": "sword-shield"
        }
      ],
      "tutor": [
        {
          "name": "burning-jealousy",
          "gen": "sword-shield"
        },
        {
          "name": "lash-out",
          "gen": "sword-shield"
        }
      ],
      "egg": []
    },
    "size": {
      "height": 1.2,
      "weight": 19.9,
      "category": "medium",
      "type": "height"
    },
    "captureRate": 127,
    "eggGroups": [
      "ground"
    ],
    "genderRatio": 4,
    "evolutions": {
      "full": {
        "name": "nickit",
        "details": null,
        "evolutions": [
          {
            "name": "thievul",
            "details": {
              "gender": null,
              "item": null,
              "knownMove": null,
              "level": 18
            },
            "evolutions": []
          }
        ]
      }
    },
    "number": 828,
    "slug": "",
    "traits": [],
    "diet": [],
    "abilities": {
      "starting": [],
      "basic": [],
      "advanced": [],
      "master": []
    },
    "movement": {
      "primary": [],
      "secondary": []
    },
    "skills": {},
    "habitats": []
  },
  "_id": "CBSbMMFL2z9YHUUh",
  "effects": [],
  "folder": null,
  "sort": 0,
  "ownership": {
    "default": 0,
    "tXAZ3QUgjuwX4gdV": 3
  },
  "flags": {
    "core": {
      "sourceId": "Compendium.ptr2e.core-species.Item.CBSbMMFL2z9YHUUh"
    }
  },
  "_stats": {
    "coreVersion": "12.318",
    "systemId": "ptr2e",
    "systemVersion": "0.001",
    "createdTime": 1712331093837,
    "modifiedTime": 1712331093837,
    "lastModifiedBy": "tXAZ3QUgjuwX4gdV"
  },
  "_key": "!items!CBSbMMFL2z9YHUUh"
}
