{
  "name": "Coil",
  "type": "move",
  "img": "systems/ptr2e/img/svg/poison_icon.svg",
  "system": {
    "slug": "coil",
    "description": "Effect: The user's ATK stage, DEF stage and ACC stage are increased by +1 for 5 activations.",
    "traits": [],
    "actions": [
      {
        "slug": "coil",
        "name": "Coil",
        "type": "attack",
        "traits": [],
        "range": {
          "target": "self",
          "distance": 0,
          "unit": "m"
        },
        "cost": {
          "activation": "complex",
          "powerPoints": 5,
          "delay": null,
          "priority": null,
          "trigger": null
        },
        "category": "status",
        "power": null,
        "accuracy": null,
        "types": [
          "poison"
        ],
        "description": "Effect: The user's ATK stage, DEF stage and ACC stage are increased by +1 for 5 activations.",
        "contestType": "",
        "contestEffect": "",
        "free": false,
        "slot": null
      }
    ],
    "container": null,
    "grade": "C"
  },
  "_id": "7r57DxIctmNSW2oV",
  "effects": []
}