{
  "name": "Destiny Bond",
  "type": "move",
  "img": "systems/ptr2e/img/svg/ghost_icon.svg",
  "system": {
    "slug": "destiny-bond",
    "actions": [
      {
        "slug": "destiny-bond",
        "name": "Destiny Bond",
        "type": "attack",
        "traits": [
          "pp-updated"
        ],
        "range": {
          "target": "creature",
          "distance": 10,
          "unit": "m"
        },
        "cost": {
          "activation": "complex",
          "powerPoints": 4
        },
        "category": "status",
        "power": null,
        "accuracy": null,
        "types": [
          "ghost"
        ],
        "description": "<p>Effect: The target gains @Affliction[destined] 3.</p>",
        "contestType": "",
        "contestEffect": "",
        "free": false,
        "slot": null
      }
    ],
    "container": null,
    "grade": "B"
  },
  "_id": "KtSSIe0Sc2Ucby1Q",
  "effects": []
}