{
    "_id": "RHcJxk6rp0XKso8R",
    "type": "move",
    "name": "Ember",
    "img": "/systems/ptr2e/img/icons/fire_icon.png",
    "system": {
        "slug": "move",
        "description": "On hit, the target has a 10% chance of being Burned 5!",
        "actions": [
            {
                "slug": "ember",
                "name": "Ember",
                "type": "attack",
                "traits": [
                    "basic",
                    "missile"
                ],
                "range": {
                    "target": "enemy",
                    "distance": 5,
                    "unit": "m"
                },
                "cost": {
                    "activation": "simple",
                    "powerPoints": 1
                },
                "category": "special",
                "power": 40,
                "accuracy": 100,
                "types": [
                    "fire"
                ],
                "description": "On hit, the target has a 10% chance of being Burned 5."
            }
        ],
        "traits": [
            "basic",
            "missile"
        ]
    },
    "effects": []
}