{
  "name": "Glare",
  "type": "move",
  "img": "/systems/ptr2e/img/svg/normal_icon.svg",
  "system": {
    "slug": "glare",
    "description": "Effect: All valid targets gain Paralysis 5 and gain Fear 2.",
    "traits": [
      "social",
      "friendly"
    ],
    "actions": [
      {
        "slug": "glare",
        "name": "Glare",
        "type": "attack",
        "traits": [
          "social",
          "friendly"
        ],
        "range": {
          "target": "cone",
          "distance": 6,
          "unit": "m"
        },
        "cost": {
          "activation": "complex",
          "powerPoints": 3,
          "delay": null,
          "priority": null,
          "trigger": null
        },
        "category": "status",
        "power": null,
        "accuracy": 100,
        "types": [
          "normal"
        ],
        "description": "Effect: All valid targets gain Paralysis 5 and gain Fear 2.",
        "contestType": "",
        "contestEffect": "",
        "free": false,
        "slot": null
      }
    ],
    "container": null,
    "grade": "E"
  },
  "_id": "i9HIVBx3gypbuBom",
  "effects": []
}