{
  "name": "Max Lob!",
  "type": "move",
  "img": "/systems/ptr2e/img/icons/untyped_icon.png",
  "system": {
    "slug": "max-lob",
    "description": "Effect: The user temporarily recalls a target within Range into an energized Max Ball. Then, the user may throw the target's Ball a distance up to 150% of the user's Fling Range and send the target out, centered on that spot, wherein the target uses Become Giant! as a Free Aciton.",
    "traits": [
      "phenomenon",
      "command"
    ],
    "actions": [
      {
        "slug": "max-lob",
        "name": "Max Lob!",
        "type": "attack",
        "traits": [
          "phenomenon",
          "command"
        ],
        "range": {
          "target": "ally",
          "distance": 20,
          "unit": "m"
        },
        "cost": {
          "activation": "complex",
          "powerPoints": 5,
          "delay": null,
          "priority": null,
          "trigger": null
        },
        "category": "status",
        "power": null,
        "accuracy": null,
        "types": [
          "untyped"
        ],
        "description": "Effect: The user temporarily recalls a target within Range into an energized Max Ball. Then, the user may throw the target's Ball a distance up to 150% of the user's Fling Range and send the target out, centered on that spot, wherein the target uses Become Giant! as a Free Aciton.",
        "contestType": "",
        "contestEffect": "",
        "free": false,
        "slot": null
      }
    ],
    "container": null
  },
  "_id": "fRSLzqIPY0XdBilp",
  "effects": []
}