{
  "name": "Metal Whip",
  "type": "move",
  "img": "/systems/ptr2e/img/svg/steel_icon.svg",
  "system": {
    "slug": "metal-whip",
    "description": "",
    "traits": [],
    "actions": [
      {
        "slug": "metal-whip",
        "name": "Metal Whip",
        "type": "attack",
        "traits": [
          "pp-updated"
        ],
        "range": {
          "target": "creature",
          "distance": 3,
          "unit": "m"
        },
        "cost": {
          "activation": "complex",
          "powerPoints": 2,
          "delay": null,
          "priority": null,
          "trigger": null
        },
        "category": "physical",
        "power": 50,
        "accuracy": 85,
        "types": [
          "steel"
        ],
        "description": "Effect: The Target becomes @Affliction[bound] 5. While the target is @Affliction[bound], they take a Tick of HP damage at the end of each of their activations. If used at melee range, the user auto-succeeds on a Grapple Maneuver check against the target if this attack hits. If either the @Affliction[grapple] or @Affliction[bound] condition ends, the target loses the other condition.",
        "contestType": "",
        "contestEffect": "",
        "free": false,
        "slot": null
      }
    ],
    "container": null,
    "grade": "E"
  },
  "_id": "wm3vkiBKzww4NiOP",
  "effects": []
}