{
  "name": "Phantom Force",
  "type": "move",
  "img": "/systems/ptr2e/img/icons/ghost_icon.png",
  "system": {
    "slug": "phantom-force",
    "description": "Effect: Set-Up: The user gains Invisible 1, and ends their activation. While in this state, they have +4 EVA stages.\nResolution: On their next activation, the user freely Moves up to one-and-a-half times the Movement Score of their choice and attacks with and resolve Phantom Force. This attack ignores the effects of [Shield] attacks when applying damage.",
    "traits": [
      "set-up",
      "crushing",
      "contact"
    ],
    "actions": [
      {
        "slug": "phantom-force",
        "name": "Phantom Force",
        "type": "attack",
        "traits": [
          "set-up",
          "crushing",
          "contact"
        ],
        "range": {
          "target": "creature",
          "distance": 1,
          "unit": "m"
        },
        "cost": {
          "activation": "complex",
          "powerPoints": 7,
          "delay": null,
          "priority": null,
          "trigger": null
        },
        "category": "physical",
        "power": 90,
        "accuracy": 100,
        "types": [
          "ghost"
        ],
        "description": "Effect: Set-Up: The user gains Invisible 1, and ends their activation. While in this state, they have +4 EVA stages.\nResolution: On their next activation, the user freely Moves up to one-and-a-half times the Movement Score of their choice and attacks with and resolve Phantom Force. This attack ignores the effects of [Shield] attacks when applying damage.",
        "contestType": "",
        "contestEffect": "",
        "free": false,
        "slot": null
      }
    ],
    "container": null,
    "grade": "A"
  },
  "_id": "hK17tJ4kinDuhKyh",
  "effects": []
}