{
    "name": "Pure Power",
    "type": "ability",
    "system": {
        "actions": [
            {
                "name": "Pure Power",
                "slug": "pure-power",
                "type": "passive",
                "cost": {
                    "activation": "free",
                    "powerPoints": 0
                },
                "range": {
                    "target": "self",
                    "distance": 0,
                    "unit": "m"
                },
                "traits": []
            }
        ],
        "description": "The user's Physical-category attacks have 25% more Power.",
        "traits": []
    },
    "_id": "IpXH3xteGYspqMKr",
    "img": "/systems/ptr2e/img/icons/ability_icon.webp",
    "effects": [],
    "folder": null
}