{
	"_id": "C5GdTKlvQQEDHt7d",
	"name": "Sturdy",
	"img": "/systems/ptr2e/img/icons/ability_icon.webp",
	"system": {
		"slug": "sturdy",
		"actions": [
			{
				"slug": "sturdy",
				"name": "Sturdy",
				"description": "Connection - Endure. When using Endure as an Interrupt action, the user can spend 2 additional AP to prevent their HP from falling below 1/2 their Max HP for the triggering attack.",
				"traits": [
					"defensive"
				],
				"type": "combat",
				"range": null,
				"cost": {
					"activation": "passive",
					"powerPoints": 0,
					"trigger": null,
					"delay": null,
					"priority": null
				}
			}
		]
	},
	"type": "ability",
	"flags": {
		"core": {
			"sourceId": "Compendium.ptr2e.core-abilities.Item.C5GdTKlvQQEDHt7d"
		}
	},
	"effects": []
}